README.rst
setup.py
nose2dep/__init__.py
nose2dep/core.py
nose2dep.egg-info/PKG-INFO
nose2dep.egg-info/SOURCES.txt
nose2dep.egg-info/dependency_links.txt
nose2dep.egg-info/requires.txt
nose2dep.egg-info/top_level.txt