Metadata-Version: 1.0
Name: nose2dep
Version: 0.2.2
Summary: The nosedep test dependency tool, ported to nose2
Home-page: https://github.com/rkday/nose2dep
Author: Rob Day
Author-email: rkd@rkd.me.uk
License: MIT
Platform: UNKNOWN
